plfatools/__init__.py
plfatools/__main__.py
plfatools/aggregator.py
tests/__init__.py
tests/test_aggregator.py
plfatools-0.1.0.dist-info/LICENSE.txt
plfatools-0.1.0.dist-info/METADATA
plfatools-0.1.0.dist-info/WHEEL
plfatools-0.1.0.dist-info/entry_points.txt
plfatools-0.1.0.dist-info/top_level.txt
plfatools-0.1.0.dist-info/RECORD
