Metadata-Version: 2.1
Name: plfatools
Version: 0.1.0
Summary: This package automates the aggregation of output from MIDI Inc. Sherlock PLFA Analysis Software into a single csv file.
Home-page: https://github.com/cafltar/plfa_tools_aggregator
Author: Patrick Morrell, Bryan Carlson
Author-email: bryan.carlson@usda.gov
License: CC0
Download-URL: https://github.com/cafltar/plfa_tools_aggregator.git
Keywords: Aggregator,PLFA,CSV
Platform: UNKNOWN
Classifier: Development Status :: 4 - Beta
Classifier: Intended Audience :: Science/Research
Classifier: Topic :: Scientific/Engineering
Classifier: Topic :: Scientific/Engineering :: Bio-Informatics
Classifier: License :: CC0 1.0 Universal (CC0 1.0) Public Domain Dedication
Classifier: Programming Language :: Python :: 3
Requires-Dist: pathlib
Requires-Dist: pandas
Requires-Dist: numpy
